ezshapes/__init__.py
ezshapes/colordict.py
ezshapes/renderer.py
ezshapes/screen.py
ezshapes-1.0.2.dist-info/METADATA
ezshapes-1.0.2.dist-info/WHEEL
ezshapes-1.0.2.dist-info/licenses/LICENSE
ezshapes-1.0.2.dist-info/RECORD
