Metadata-Version: 2.4
Name: ezshapes
Version: 1.0.2
Summary: A pygame wrapper to simplify the library's draw functions.
Project-URL: Homepage, https://github.com/gmarzo/ezshapes
Project-URL: Issues, https://github.com/gmarzo/ezshapes/issues
Author-email: Garrett Marzo <garrett.marzo@gmail.com>
License-File: LICENSE
Classifier: License :: OSI Approved :: MIT License
Classifier: Operating System :: OS Independent
Classifier: Programming Language :: Python :: 3
Requires-Python: >=3.8
Requires-Dist: pygame>=2.6.1
